andyao/mdspliter/tree/node.py
andyao.mdspliter.tree-0.1.0.dist-info/LICENSE
andyao.mdspliter.tree-0.1.0.dist-info/WHEEL
andyao.mdspliter.tree-0.1.0.dist-info/METADATA
andyao.mdspliter.tree-0.1.0.dist-info/RECORD
