Metadata-Version: 2.1
Name: andyao.mdspliter.tree
Version: 0.1.0
Summary: Tree data structure for mdsplitter.
Author: zen96285
Author-email: zen96285@gmail.com
Requires-Python: >=3.6,<4.0
Classifier: Programming Language :: Python :: 3
Classifier: Programming Language :: Python :: 3.6
Classifier: Programming Language :: Python :: 3.7
Classifier: Programming Language :: Python :: 3.8
Classifier: Programming Language :: Python :: 3.9
